openfdem/__init__.py
openfdem/aa_test_fdem.py
openfdem/aggregate_storage.py
openfdem/complete_BD_thread_pool_generators.py
openfdem/complete_PLT_thread_pool_generators.py
openfdem/complete_UCS_thread_pool_generators.py
openfdem/direct_shear_thread_pool_generators.py
openfdem/extract_cell_thread_pool_generators.py
openfdem/extract_thread_pool_generators.py
openfdem/extract_threshold_thread_pool_generators.py
openfdem/formatting_codes.py
openfdem/model_reader.py
openfdem/openfdem.py
openfdem/setup.py
pyFDEMvisualizer-5.1.dist-info/METADATA
pyFDEMvisualizer-5.1.dist-info/WHEEL
pyFDEMvisualizer-5.1.dist-info/top_level.txt
pyFDEMvisualizer-5.1.dist-info/RECORD
