Metadata-Version: 2.1
Name: pyFDEMvisualizer
Version: 5.1
Summary: Wheel file of pyFDEMvisualizer modules 5.1
Home-page: UNKNOWN
Author: University of Toronto, 2022
License: UNKNOWN
Platform: UNKNOWN
Requires-Python: >=3.5,<=3.9
Requires-Dist: joblib
Requires-Dist: numpy (>=1.0)
Requires-Dist: pandas (>=0.0)
Requires-Dist: pyvista (>=0.20)
Requires-Dist: tqdm
